cythLeastR.cpython-312-darwin.so
cythonKronPlus.cpython-312-darwin.so
py_SPSPaRTAN-1.0.0.dist-info/LICENSE.txt
py_SPSPaRTAN-1.0.0.dist-info/METADATA
py_SPSPaRTAN-1.0.0.dist-info/WHEEL
py_SPSPaRTAN-1.0.0.dist-info/top_level.txt
py_SPSPaRTAN-1.0.0.dist-info/RECORD
